LICENSE
MANIFEST.in
README.rst
setup.py
django_requestlogging/__init__.py
django_requestlogging/logging_filters.py
django_requestlogging/middleware.py
django_requestlogging/models.py
django_requestlogging/tests.py
django_requestlogging.egg-info/PKG-INFO
django_requestlogging.egg-info/SOURCES.txt
django_requestlogging.egg-info/dependency_links.txt
django_requestlogging.egg-info/requires.txt
django_requestlogging.egg-info/top_level.txt
django_requestlogging.egg-info/zip-safe