Metadata-Version: 1.1
Name: django-requestlogging
Version: 1.0.1
Summary: Adds information about requests to logging records.
Home-page: http://bitbucket.org/trustcentric/django-requestlogging/
Author: TrustCentric
Author-email: admin@trustcentric.com
License: UNKNOWN
Platform: UNKNOWN
Classifier: Development Status :: 5 - Production/Stable
Classifier: Environment :: Web Environment
Classifier: Framework :: Django
Classifier: License :: OSI Approved :: BSD License
Classifier: Operating System :: OS Independent
Classifier: Programming Language :: Python
